setup.py
grepo/__init__.py
grepo/args.py
grepo/grepo.py
grepo.egg-info/PKG-INFO
grepo.egg-info/SOURCES.txt
grepo.egg-info/dependency_links.txt
grepo.egg-info/entry_points.txt
grepo.egg-info/pbr.json
grepo.egg-info/top_level.txt