Metadata-Version: 1.0
Name: grepo
Version: 0.3.0
Summary: Grepo grep and peco tool
Home-page: https://github.com/vivainio/grepo
Author: Ville Vainio
Author-email: vivainio@gmail.com
License: UNKNOWN
Platform: UNKNOWN
